access/__init__.py
access/user_finder.py
access/windows_audit.py
alerts/__init__.py
alerts/notifier.py
integrity/__init__.py
integrity/verifier.py
utils/__init__.py
utils/config.py
watcher/__init__.py
watcher/cross_platform_watcher.py
watcher/windows_watcher.py
file_monitor_sys-0.1.4.dist-info/METADATA
file_monitor_sys-0.1.4.dist-info/WHEEL
file_monitor_sys-0.1.4.dist-info/top_level.txt
file_monitor_sys-0.1.4.dist-info/RECORD
